git_bbb/__init__.py
git_bbb/browser.py
git_bbb/cli.py
git_bbb/git_plumbing.py
git_bbb/key_bindings.py
git_bbb/undo_redo.py
git_bbb-0.0.10.dist-info/LICENSE
git_bbb-0.0.10.dist-info/METADATA
git_bbb-0.0.10.dist-info/WHEEL
git_bbb-0.0.10.dist-info/entry_points.txt
git_bbb-0.0.10.dist-info/top_level.txt
git_bbb-0.0.10.dist-info/RECORD
