Metadata-Version: 2.1
Name: git-bbb
Version: 0.0.10
Summary: ⚡ Brisk Blame Browser for Git
Maintainer-email: Błażej Michalik <code.mrmino@gmail.com>
License:                     GNU GENERAL PUBLIC LICENSE
Project-URL: repository, https://github.com/MrMino/git-bbb
Project-URL: changelog, https://github.com/MrMino/git-bbb/blob/master/CHANGELOG.md
Requires-Python: >=3.7
License-File: LICENSE
Requires-Dist: gitpython
Requires-Dist: Pygments
Requires-Dist: prompt-toolkit
Requires-Dist: click~=8.1
Provides-Extra: test
Requires-Dist: pytest; extra == "test"
